vnpy_akshare/__init__.py
vnpy_akshare/akshare_datafeed.py
vnpy_akshare_adapter-1.0.0.dist-info/licenses/LICENSE
vnpy_akshare_adapter-1.0.0.dist-info/METADATA
vnpy_akshare_adapter-1.0.0.dist-info/WHEEL
vnpy_akshare_adapter-1.0.0.dist-info/top_level.txt
vnpy_akshare_adapter-1.0.0.dist-info/RECORD
