Metadata-Version: 2.4
Name: vnpy_akshare_adapter
Version: 1.0.0
Summary: AKShare数据服务接口 - VeighNa框架的数据接口适配
Home-page: https://github.com/wade1010/vnpy_akshare
Author: wade1010
Author-email: 640297@qq.com
License: MIT
Keywords: vnpy,quant,akshare,trading,investment
Classifier: Development Status :: 5 - Production/Stable
Classifier: Operating System :: OS Independent
Classifier: Programming Language :: Python :: 3
Classifier: Programming Language :: Python :: 3.7
Classifier: Programming Language :: Python :: 3.8
Classifier: Programming Language :: Python :: 3.9
Classifier: Programming Language :: Python :: 3.10
Classifier: Topic :: Office/Business :: Financial :: Investment
Classifier: License :: OSI Approved :: MIT License
Requires-Python: >=3.10
License-File: LICENSE
Requires-Dist: vnpy>=4.0.0
Requires-Dist: akshare>=1.16.98
Dynamic: author
Dynamic: author-email
Dynamic: classifier
Dynamic: description
Dynamic: description-content-type
Dynamic: home-page
Dynamic: keywords
Dynamic: license
Dynamic: license-file
Dynamic: requires-dist
Dynamic: requires-python
Dynamic: summary
